Login/__init__.py
Login/admin.py
Login/apps.py
Login/forms.py
Login/models.py
Login/tests.py
Login/urls.py
Login/views.py
Login/Templates/404.html
Login/Templates/500.html
Login/Templates/base.html
Login/Templates/change-password.html
Login/Templates/emailtemplate.html
Login/Templates/html_password_reset_email.html
Login/Templates/login.html
Login/Templates/password_reset.html
Login/Templates/password_reset_complete.html
Login/Templates/password_reset_confirm.html
Login/Templates/password_reset_done.html
Login/Templates/password_reset_form.html
Login/Templates/password_reset_subject.txt
Login/Templates/register.html
Login/migrations/0001_initial.py
Login/migrations/0002_alter_userprofile_employeeid.py
Login/migrations/0003_auto_20211016_1810.py
Login/migrations/0004_alter_userprofile_gender.py
Login/migrations/__init__.py
Login/static/404img.jpg
Login/static/bgimg4.jpg
Login/static/favicon.ico
Login/static/logo.jpg
Login/static/css/footer.css
Login/static/css/style.css
django_nandy_login-0.2.0.dist-info/LICENSE
django_nandy_login-0.2.0.dist-info/METADATA
django_nandy_login-0.2.0.dist-info/WHEEL
django_nandy_login-0.2.0.dist-info/top_level.txt
django_nandy_login-0.2.0.dist-info/RECORD
